pyjssp/__init__.py
pyjssp/benchmarks.py
pyjssp/configs.py
pyjssp/jobShopSamplers.py
pyjssp/machineHelpers.py
pyjssp/operationHelpers.py
pyjssp/simulators.py
pyjssp/utils.py
pyjssp-0.5.1.dist-info/METADATA
pyjssp-0.5.1.dist-info/WHEEL
pyjssp-0.5.1.dist-info/top_level.txt
pyjssp-0.5.1.dist-info/RECORD
